{
":angry": "angry.gif",
":angst": "angst.gif",
":asian": "asian.gif",
"^^": "asian.gif",
":badmind": "badmind.gif",
":baeh": "baeh.gif",
":bandit": "bandit.gif",
":beam": "beam.gif",
":bier": "bier.gif",
":bigass": "bigass.gif",
":blablabla": "blablabla.gif",
":blinzel": "blinzel.gif",
":bös": "boes.gif",
":bounce": "bounce.gif",
":brain": "brain.gif",
":cheer": "cheer.gif",
":danke": "danke.gif",
":debil": "debil.gif",
":doppelbounce": "doppelbounce.gif",
":doppelhammer": "doppelhammer.gif",
":eek": "eek.gif",
":enttaeuscht": "enttaeuscht.gif",
":-((": "enttaeuscht.gif",
":fiesebotten": "fiesebotten.gif",
":five": "five.gif",
":freu": "freu.gif",
":freuen": "freuen.gif",
":fuckoff": "fuckoff.gif",
":gumbo": "gumbo.gif",
":haha": "haha.gif",
":hammer": "hammer.gif",
":hammer2": "hammer2.gif",
":headspin": "headspin.gif",
":heul": "heul.gif",
":hinundher": "hinundher.gif",
":hm": "hm.gif",
":hoar": "hoar.gif",
":hörthört": "hoerthoert.gif",
":honks": "honks.gif",
":huhu": "huhu.gif",
":ja": "ja.gif",
":jump": "jump.gif",
":jump2": "jump2.gif",
":koch": "koch.gif",
":koch2": "koch2.gif",
":kopfstand": "kopfstand.gif",
":kotz": "kotz.gif",
":kuss": "kuss.gif",
":laber": "laber.gif",
":leuchtturm": "leuchtturm.gif",
":leuchtturm2": "leuchtturm2.gif",
":lol": "lol.gif",
":lol2": "lol2.gif",
":lol3": "lol3.gif",
":lol4": "lol4.gif",
":love": "love.gif",
":metal": "metal.gif",
":mrwong": "mrwong.gif",
":musik": "musik.gif",
":nana": "nana.gif",
":nein": "nein.gif",
":nene": "nene.gif",
":nervös": "nervoes.gif",
":nudgenudge": "nudgenudge.gif",
":ohno": "ohno.gif",
":ouw": "ouw.gif",
":pah": "pah.gif",
":para": "para.gif",
":party": "party.gif",
":pee": "pee.gif",
":pee2": "pee2.gif",
":peng": "peng.gif",
":pfeif": "pfeif.gif",
":planlos": "planlos.gif",
":pumpkin": "pumpkin.gif",
":rafftnix": "rafftnix.gif",
":rockon": "rockon.gif",
":rrr": "rrr.gif",
":sauer": "sauer.gif",
":schimpf": "schimpf.gif",
":schimpf2": "schimpf2.gif",
":schnellweg": "schnellweg.gif",
":schonklar": "schonklar.gif",
":scream": "scream.gif",
":sehrfreuen": "sehrfreuen.gif",
":sing": "singen.gif",
":smile": "smile.gif",
":-)": "smile.gif",
":bigsmile": "smiler.gif",
":smoke": "smoke.gif",
":starr": "starr.gif",
":staunen": "staunen.gif",
":-O": "staunen.gif",
":stumm": "stumm.gif",
":toni": "toni.gif",
":traurig": "traurig.gif",
":trippel": "trippel.gif",
":troesten": "troesten.gif",
":tröst": "troesten.gif",
":tuschel": "tuschel.gif",
":tuse": "tuse.gif",
":tv": "tv.gif",
":umarm": "umarm.gif",
":vampir": "vampir.gif",
":verlegen": "verlegen.gif",
":hide": "verstecken.gif",
":vogel": "vogel.gif",
":wemeln": "wemeln.gif",
":werber": "werber.gif",
":zeigefinger": "zeigefinger.gif",
":zellteilung": "zellteilung.gif",
":zipper": "zipper.gif",
":zombie": "zombie.gif",
":zorn": "zorn.gif",
":zunge": "zunge.gif",
":zwinker": "zwinker.gif",
":zzz": "zzz.gif",
":-D": "freuen.gif",
":-(": "traurig.gif",
":-P": "baeh.gif"
}